xarray_topo-0.0.10.dist-info/DESCRIPTION.rst
xarray_topo-0.0.10.dist-info/METADATA
xarray_topo-0.0.10.dist-info/RECORD
xarray_topo-0.0.10.dist-info/WHEEL
xarray_topo-0.0.10.dist-info/metadata.json
xarray_topo-0.0.10.dist-info/top_level.txt
xtopo/__init__.py
xtopo/_version.py
xtopo/algos/__init__.py
xtopo/algos/_graph_mst.py
xtopo/algos/_union_find.py
xtopo/algos/bedrock_channel.py
xtopo/algos/flow_routing.py
xtopo/algos/hillslope_erosion.py
xtopo/algos/utils.py
xtopo/models/__init__.py
xtopo/models/fastscape_base.py
